argox/__init__.py
argox/argo.py
argox/example.py
argox/test.py
argox/cmsDetect/__init__.py
argox/cmsDetect/cmsDetect.py
argox/pyffuf/__init__.py
argox/pyffuf/checker.py
argox/pyffuf/pyffuf.py
argox/pyffuf/wordcounter.py
argox/reverse/__init__.py
argox/reverse/reverse.py
argox/scoketscanner/__init__.py
argox/scoketscanner/socketscanner.py
argox/spider/__init__.py
argox/spider/spider.py
AGROX-1.9.dist-info/LICENSE
AGROX-1.9.dist-info/METADATA
AGROX-1.9.dist-info/WHEEL
AGROX-1.9.dist-info/top_level.txt
AGROX-1.9.dist-info/RECORD
